laze/__init__.py
laze/build.py
laze/common.py
laze/constants.py
laze/create.py
laze/debug.py
laze/deepcopy.py
laze/dep.py
laze/dl.py
laze/generate.py
laze/laze.py
laze/mtimelog.py
laze/util.py
laze/yaml.py
laze/data/default/laze.yml
laze-0.0.12.dist-info/METADATA
laze-0.0.12.dist-info/WHEEL
laze-0.0.12.dist-info/entry_points.txt
laze-0.0.12.dist-info/top_level.txt
laze-0.0.12.dist-info/RECORD
