Metadata-Version: 2.1
Name: laze
Version: 0.0.12
Summary: laze: a ninja buildfile generator
Home-page: https://github.com/kaspar030/laze
Author: Kaspar Schleiser
Author-email: kaspar@schleiser.de
License: GPLv3
Keywords: build tool
Platform: UNKNOWN
Classifier: Development Status :: 3 - Alpha
Classifier: Intended Audience :: Developers
Classifier: Topic :: Software Development :: Build Tools
Classifier: License :: OSI Approved :: GNU General Public License v3 (GPLv3)
Classifier: Programming Language :: Python :: 3.4
Classifier: Programming Language :: Python :: 3.5
Classifier: Programming Language :: Python :: 3.6
Classifier: Programming Language :: Python :: 3.7
Requires-Dist: click
Requires-Dist: pyyaml
Requires-Dist: ninja-syntax
Requires-Dist: click-default-group
Requires-Dist: msgpack
